[
  {
    "image": "E:\\RA\\social_media_analysis\\Ontology_analysis\\image_recognition_dataset\\3x2be3z62c2sef2\\video\\3x2be3z62c2sef2_semantic_frame_000005.jpg",
    "visual_analysis": {
      "objects": {
        "disaster-relevant": [
          "被淹的的汽车",
          "积水道路"
        ],
        "general": []
      },
      "scenes": [
        "积水街道"
      ],
      "events": [],
      "time": [
        "白天"
      ],
      "text-overlay": [
        "陆源金属制品",
        "1亿辰泰保护膜"
      ]
    },
    "ontology": {
      "concepts": {
        "time": [
          "白天"
        ],
        "infrastructure": [
          "积水街道",
          "商铺"
        ],
        "personnel": [],
        "hazard": [
          "积水"
        ],
        "environment": [],
        "response_equipment": [],
        "location": [],
        "activity": []
      },
      "attributes": [
        {
          "concept": "道路",
          "status": "积水",
          "risk_level": "高",
          "visibility": "一般",
          "terrain_condition": "积水"
        }
      ],
      "relations": [
        {
          "subject": "被淹的的汽车",
          "predicate": "in",
          "object": "积水街道"
        },
        {
          "subject": "商铺",
          "predicate": "near",
          "object": "积水街道"
        }
      ],
      "inferences": [
        {
          "condition": "道路被淹",
          "consequence": "交通中断",
          "action": "启用备用路线，提供救援设备"
        }
      ]
    }
  },
  {
    "image": "E:\\RA\\social_media_analysis\\Ontology_analysis\\image_recognition_dataset\\3x2be3z62c2sef2\\video\\3x2be3z62c2sef2_semantic_frame_000009.jpg",
    "visual_analysis": {
      "objects": {
        "disaster-relevant": [
          "被淹的的汽车",
          "积水的道路"
        ],
        "general": []
      },
      "scenes": [
        "积水街道"
      ],
      "events": [],
      "time": [
        "白天"
      ],
      "text-overlay": []
    },
    "ontology": {
      "concepts": {
        "time": [
          "白天"
        ],
        "infrastructure": [
          "道路",
          "建筑物"
        ],
        "personnel": [],
        "hazard": [
          "积水"
        ],
        "environment": [],
        "response_equipment": [],
        "location": [],
        "activity": []
      },
      "attributes": [
        {
          "concept": "道路",
          "status": "积水",
          "risk_level": "高",
          "visibility": "一般",
          "terrain_condition": "积水"
        }
      ],
      "relations": [
        {
          "subject": "被淹的的汽车",
          "predicate": "in",
          "object": "积水街道"
        },
        {
          "subject": "建筑物",
          "predicate": "near",
          "object": "积水街道"
        }
      ],
      "inferences": [
        {
          "condition": "道路被淹",
          "consequence": "交通中断",
          "action": "启用备用路线，提供救援设备"
        }
      ]
    }
  },
  {
    "image": "E:\\RA\\social_media_analysis\\Ontology_analysis\\image_recognition_dataset\\3x2be3z62c2sef2\\video\\3x2be3z62c2sef2_semantic_frame_000010.jpg",
    "visual_analysis": {
      "objects": {
        "disaster-relevant": [
          "被淹的的道路",
          "漂浮的垃圾桶"
        ],
        "general": []
      },
      "scenes": [
        "积水街道"
      ],
      "events": [
        "道路积水"
      ],
      "time": [
        "白天"
      ],
      "text-overlay": []
    },
    "ontology": {
      "concepts": {
        "time": [
          "白天"
        ],
        "infrastructure": [
          "被淹的的道路"
        ],
        "hazard": [
          "积水"
        ],
        "environment": [],
        "response_equipment": [],
        "location": [],
        "activity": []
      },
      "attributes": [
        {
          "concept": "道路",
          "status": "积水",
          "risk_level": "高",
          "visibility": "一般",
          "terrain_condition": "积水"
        }
      ],
      "relations": [
        {
          "subject": "漂浮的垃圾桶",
          "predicate": "in",
          "object": "积水街道"
        },
        {
          "subject": "被淹的的道路",
          "predicate": "is_a",
          "object": "积水影响区域"
        }
      ],
      "inferences": [
        {
          "condition": "道路严重积水",
          "consequence": "交通中断，行人和车辆无法通行",
          "action": "疏散周边居民，禁止非必要出行，准备抽水设备"
        }
      ]
    }
  },
  {
    "image": "E:\\RA\\social_media_analysis\\Ontology_analysis\\image_recognition_dataset\\3x2be3z62c2sef2\\video\\3x2be3z62c2sef2_semantic_frame_000011.jpg",
    "visual_analysis": {
      "objects": {
        "disaster-relevant": [
          "被淹的的卡车",
          "积水道路"
        ],
        "general": []
      },
      "scenes": [
        "积水街道"
      ],
      "events": [],
      "time": [
        "白天"
      ],
      "text-overlay": []
    },
    "ontology": {
      "concepts": {
        "time": [
          "白天"
        ],
        "infrastructure": [
          "积水街道",
          "被淹的的卡车"
        ],
        "personnel": [],
        "hazard": [
          "积水"
        ],
        "environment": [],
        "response_equipment": [],
        "location": [],
        "activity": []
      },
      "attributes": [
        {
          "concept": "道路",
          "status": "积水",
          "risk_level": "高",
          "visibility": "一般",
          "terrain_condition": "积水"
        },
        {
          "concept": "卡车",
          "status": "被淹的",
          "risk_level": "中",
          "visibility": "清晰",
          "terrain_condition": "积水"
        }
      ],
      "relations": [
        {
          "subject": "被淹的的卡车",
          "predicate": "in",
          "object": "积水街道"
        },
        {
          "subject": "积水",
          "predicate": "causes",
          "object": "道路积水"
        }
      ],
      "inferences": [
        {
          "condition": "道路被淹",
          "consequence": "交通中断",
          "action": "疏散受困人员，启用备用路线"
        }
      ]
    }
  },
  {
    "image": "E:\\RA\\social_media_analysis\\Ontology_analysis\\image_recognition_dataset\\3x2be3z62c2sef2\\video\\3x2be3z62c2sef2_semantic_frame_000015.jpg",
    "visual_analysis": {
      "objects": {
        "disaster-relevant": [
          "被淹的的道路"
        ],
        "general": []
      },
      "scenes": [
        "积水街道"
      ],
      "events": [],
      "time": [
        "白天"
      ],
      "text-overlay": []
    },
    "ontology": {
      "concepts": {
        "time": [
          "白天"
        ],
        "infrastructure": [
          "道路"
        ],
        "hazard": [
          "积水"
        ],
        "environment": [],
        "response_equipment": [],
        "location": [],
        "activity": [],
        "personnel": []
      },
      "attributes": [
        {
          "concept": "道路",
          "status": "积水",
          "risk_level": "高",
          "visibility": "一般",
          "terrain_condition": "积水"
        }
      ],
      "relations": [
        {
          "subject": "积水",
          "predicate": "affects",
          "object": "道路"
        },
        {
          "subject": "道路",
          "predicate": "in_status_of",
          "object": "积水"
        }
      ],
      "inferences": [
        {
          "condition": "道路被洪水淹没",
          "consequence": "交通中断，存在安全风险",
          "action": "疏散人员，禁止通行，准备抽水设备"
        }
      ]
    }
  },
  {
    "image": "E:\\RA\\social_media_analysis\\Ontology_analysis\\image_recognition_dataset\\3x2be3z62c2sef2\\video\\3x2be3z62c2sef2_semantic_frame_000016.jpg",
    "visual_analysis": {
      "objects": {
        "disaster-relevant": [
          "被淹的的道路",
          "被水浸泡的汽车"
        ],
        "general": []
      },
      "scenes": [
        "积水街道"
      ],
      "events": [],
      "time": [
        "白天"
      ],
      "text-overlay": []
    },
    "ontology": {
      "concepts": {
        "time": [
          "白天"
        ],
        "infrastructure": [
          "被淹的的道路",
          "被水浸泡的汽车"
        ],
        "personnel": [],
        "hazard": [
          "积水"
        ],
        "environment": [],
        "response_equipment": [],
        "location": [],
        "activity": []
      },
      "attributes": [
        {
          "concept": "道路",
          "status": "积水",
          "risk_level": "高",
          "visibility": "一般",
          "terrain_condition": "积水"
        }
      ],
      "relations": [
        {
          "subject": "被水浸泡的汽车",
          "predicate": "in",
          "object": "积水街道"
        },
        {
          "subject": "积水",
          "predicate": "causes",
          "object": "道路积水"
        }
      ],
      "inferences": [
        {
          "condition": "道路被淹",
          "consequence": "交通中断",
          "action": "疏散车辆，设置警示标志"
        }
      ]
    }
  },
  {
    "image": "E:\\RA\\social_media_analysis\\Ontology_analysis\\image_recognition_dataset\\3x2be3z62c2sef2\\video\\3x2be3z62c2sef2_semantic_frame_000018.jpg",
    "visual_analysis": {
      "objects": {
        "disaster-relevant": [
          "被淹的的街道",
          "区域浸泡的汽车"
        ],
        "general": []
      },
      "scenes": [
        "积水街道"
      ],
      "events": [],
      "time": [
        "白天"
      ],
      "text-overlay": []
    },
    "ontology": {
      "concepts": {
        "time": [
          "白天"
        ],
        "infrastructure": [
          "被淹的的街道",
          "区域浸泡的汽车"
        ],
        "personnel": [],
        "hazard": [
          "积水"
        ],
        "environment": [],
        "response_equipment": [],
        "location": [],
        "activity": []
      },
      "attributes": [
        {
          "concept": "被淹的的街道",
          "status": "积水",
          "risk_level": "高",
          "visibility": "一般",
          "terrain_condition": "积水"
        },
        {
          "concept": "区域浸泡的汽车",
          "status": "积水",
          "risk_level": "中",
          "visibility": "清晰",
          "terrain_condition": "积水"
        }
      ],
      "relations": [
        {
          "subject": "积水",
          "predicate": "causes",
          "object": "被淹的的街道"
        },
        {
          "subject": "区域浸泡的汽车",
          "predicate": "in",
          "object": "被淹的的街道"
        }
      ],
      "inferences": [
        {
          "condition": "街道严重积水",
          "consequence": "交通中断，可能影响救援行动",
          "action": "启用备用路线，派遣救援艇"
        }
      ]
    }
  },
  {
    "image": "E:\\RA\\social_media_analysis\\Ontology_analysis\\image_recognition_dataset\\3x2be3z62c2sef2\\video\\3x2be3z62c2sef2_semantic_frame_000019.jpg",
    "visual_analysis": {
      "objects": {
        "disaster-relevant": [
          "被淹的的汽车",
          "积水街道"
        ],
        "general": []
      },
      "scenes": [
        "积水街道"
      ],
      "events": [],
      "time": [
        "白天"
      ],
      "text-overlay": []
    },
    "ontology": {
      "concepts": {
        "time": [
          "白天"
        ],
        "infrastructure": [
          "积水街道",
          "被淹的的汽车"
        ],
        "personnel": [],
        "hazard": [
          "积水"
        ],
        "environment": [],
        "response_equipment": [],
        "location": [],
        "activity": []
      },
      "attributes": [
        {
          "concept": "积水街道",
          "status": "积水",
          "risk_level": "高",
          "visibility": "一般",
          "terrain_condition": "积水"
        }
      ],
      "relations": [
        {
          "subject": "被淹的的汽车",
          "predicate": "in",
          "object": "积水街道"
        },
        {
          "subject": "积水",
          "predicate": "causes",
          "object": "积水街道"
        }
      ],
      "inferences": [
        {
          "condition": "积水街道",
          "consequence": "交通中断",
          "action": "疏散车辆，设置警示标志"
        }
      ]
    }
  },
  {
    "image": "E:\\RA\\social_media_analysis\\Ontology_analysis\\image_recognition_dataset\\3x2be3z62c2sef2\\video\\3x2be3z62c2sef2_semantic_frame_000025.jpg",
    "visual_analysis": {
      "objects": {
        "disaster-relevant": [
          "被淹的的汽车"
        ],
        "general": []
      },
      "scenes": [
        "积水街道"
      ],
      "events": [],
      "time": [
        "白天"
      ],
      "text-overlay": []
    },
    "ontology": {
      "concepts": {
        "time": [
          "白天"
        ],
        "infrastructure": [
          "道路"
        ],
        "personnel": [],
        "hazard": [
          "积水"
        ],
        "environment": [],
        "response_equipment": [],
        "location": [],
        "activity": []
      },
      "attributes": [
        {
          "concept": "道路",
          "status": "积水",
          "risk_level": "高",
          "visibility": "一般",
          "terrain_condition": "积水"
        }
      ],
      "relations": [
        {
          "subject": "被淹的的汽车",
          "predicate": "in",
          "object": "积水街道"
        },
        {
          "subject": "积水",
          "predicate": "causes",
          "object": "道路积水"
        }
      ],
      "inferences": [
        {
          "condition": "道路被淹",
          "consequence": "交通中断",
          "action": "启用备用路线，疏散车辆"
        }
      ]
    }
  },
  {
    "image": "E:\\RA\\social_media_analysis\\Ontology_analysis\\image_recognition_dataset\\3x2be3z62c2sef2\\video\\3x2be3z62c2sef2_semantic_frame_000026.jpg",
    "visual_analysis": {
      "objects": {
        "disaster-relevant": [
          "救援艇"
        ],
        "general": []
      },
      "scenes": [
        "积水现场"
      ],
      "events": [],
      "time": [
        "白天"
      ],
      "text-overlay": []
    },
    "ontology": {
      "concepts": {
        "time": [
          "白天"
        ],
        "infrastructure": [],
        "personnel": [],
        "hazard": [
          "积水"
        ],
        "environment": [
          "河流"
        ],
        "response_equipment": [
          "救援艇"
        ],
        "location": [],
        "activity": []
      },
      "attributes": [
        {
          "concept": "救援艇",
          "status": "正常",
          "risk_level": "中",
          "visibility": "清晰",
          "terrain_condition": "积水"
        }
      ],
      "relations": [
        {
          "subject": "救援艇",
          "predicate": "in",
          "object": "积水现场"
        },
        {
          "subject": "救援艇",
          "predicate": "is_used_for",
          "object": "救援活动"
        }
      ],
      "inferences": [
        {
          "condition": "救援艇在洪水中行驶",
          "consequence": "可能进行人员或物资转移",
          "action": "确保救援艇的安全和有效使用，监测周围环境"
        }
      ]
    }
  },
  {
    "image": "E:\\RA\\social_media_analysis\\Ontology_analysis\\image_recognition_dataset\\3x2be3z62c2sef2\\video\\3x2be3z62c2sef2_semantic_frame_000028.jpg",
    "visual_analysis": {
      "objects": {
        "disaster-relevant": [
          "被淹的的摩托车",
          "积水街道"
        ],
        "general": []
      },
      "scenes": [
        "积水街道"
      ],
      "events": [],
      "time": [
        "白天"
      ],
      "text-overlay": []
    },
    "ontology": {
      "concepts": {
        "time": [
          "白天"
        ],
        "infrastructure": [
          "积水街道"
        ],
        "personnel": [],
        "hazard": [
          "积水"
        ],
        "environment": [],
        "response_equipment": [],
        "location": [],
        "activity": []
      },
      "attributes": [
        {
          "concept": "道路",
          "status": "积水",
          "risk_level": "高",
          "visibility": "一般",
          "terrain_condition": "积水"
        }
      ],
      "relations": [
        {
          "subject": "被淹的的摩托车",
          "predicate": "in",
          "object": "积水街道"
        },
        {
          "subject": "积水",
          "predicate": "causes",
          "object": "道路积水"
        }
      ],
      "inferences": [
        {
          "condition": "道路被淹",
          "consequence": "交通中断",
          "action": "疏散低洼区域居民，启用备用路线"
        }
      ]
    }
  },
  {
    "image": "E:\\RA\\social_media_analysis\\Ontology_analysis\\image_recognition_dataset\\3x2be3z62c2sef2\\video\\3x2be3z62c2sef2_semantic_frame_000029.jpg",
    "visual_analysis": {
      "objects": {
        "disaster-relevant": [
          "被淹的的汽车",
          "积水道路"
        ],
        "general": []
      },
      "scenes": [
        "积水街道"
      ],
      "events": [],
      "time": [
        "白天"
      ],
      "text-overlay": []
    },
    "ontology": {
      "concepts": {
        "time": [
          "白天"
        ],
        "infrastructure": [
          "积水道路",
          "被淹的的汽车"
        ],
        "personnel": [],
        "hazard": [
          "积水"
        ],
        "environment": [],
        "response_equipment": [],
        "location": [],
        "activity": []
      },
      "attributes": [
        {
          "concept": "积水道路",
          "status": "积水",
          "risk_level": "高",
          "visibility": "一般",
          "terrain_condition": "积水"
        },
        {
          "concept": "被淹的的汽车",
          "status": "积水",
          "risk_level": "中",
          "visibility": "清晰",
          "terrain_condition": "积水"
        }
      ],
      "relations": [
        {
          "subject": "被淹的的汽车",
          "predicate": "in",
          "object": "积水道路"
        },
        {
          "subject": "积水",
          "predicate": "causes",
          "object": "积水道路"
        }
      ],
      "inferences": [
        {
          "condition": "道路被淹",
          "consequence": "交通中断",
          "action": "启用备用路线，疏散车辆"
        }
      ]
    }
  }
]